actora/__init__.py
actora/actora_model.py
actora/actora_predictor.py
actora-1.0.0.dist-info/licenses/LICENSE
actora-1.0.0.dist-info/METADATA
actora-1.0.0.dist-info/WHEEL
actora-1.0.0.dist-info/top_level.txt
actora-1.0.0.dist-info/RECORD
