Metadata-Version: 2.4
Name: actora
Version: 1.0.0
Summary: Actora interface for models on Hugging Face
Home-page: https://github.com/RdivxeAI/actora
Author: mecha
Author-email: AmrTweg <ai@rdivxe.com>
License: MIT
Requires-Python: >=3.8
License-File: LICENSE
Requires-Dist: torch
Requires-Dist: transformers
Requires-Dist: numpy
Dynamic: author
Dynamic: home-page
Dynamic: license-file
Dynamic: requires-python
